my_ezql/__init__.py
my_ezql/myezql.py
tests/__init__.py
tests/test_my_ezql.py
my_ezql-0.2.6.dist-info/LICENSE
my_ezql-0.2.6.dist-info/METADATA
my_ezql-0.2.6.dist-info/WHEEL
my_ezql-0.2.6.dist-info/top_level.txt
my_ezql-0.2.6.dist-info/RECORD
