Metadata-Version: 2.1
Name: my-ezql
Version: 0.2.6
Summary: Using Mysql the easy way
Home-page: UNKNOWN
Author: Tony Hasson
Author-email: tony.hasson1@gmail.com
License: MIT
Platform: UNKNOWN
Classifier: Intended Audience :: Developers
Classifier: License :: OSI Approved :: MIT License
Classifier: Programming Language :: Python
Classifier: Programming Language :: Python :: 3
Classifier: Programming Language :: Python :: 3.8
Classifier: Programming Language :: Python :: 3.9
Classifier: Operating System :: OS Independent
License-File: LICENSE
Requires-Dist: mysql-connector-python
Requires-Dist: pandas
